dirai/__init__.py
dirai/cli.py
dirai/config.py
dirai/constants.py
dirai/scanner.py
dirai/utils.py
dirai_tool-0.0.7.dist-info/LICENSE
dirai_tool-0.0.7.dist-info/METADATA
dirai_tool-0.0.7.dist-info/WHEEL
dirai_tool-0.0.7.dist-info/entry_points.txt
dirai_tool-0.0.7.dist-info/top_level.txt
dirai_tool-0.0.7.dist-info/RECORD
