Metadata-Version: 2.2
Name: dirai-tool
Version: 0.0.7
Summary: DIRAI - Enhanced Directory Structure Analyzer with Security Features for AI Models
Author: Salahaldain Alhajj
Author-email: contact@salahaldain.com
Classifier: Programming Language :: Python :: 3
Classifier: License :: OSI Approved :: MIT License
Classifier: Operating System :: OS Independent
Requires-Python: >=3.8
License-File: LICENSE
Requires-Dist: PyYAML>=6.0
Requires-Dist: pathspec>=0.9.0
Dynamic: author
Dynamic: author-email
Dynamic: classifier
Dynamic: description
Dynamic: description-content-type
Dynamic: requires-dist
Dynamic: requires-python
Dynamic: summary
